{
 "title": "MissionControl",
 "description": "Use controllers from other consoles",
 "author": "ndeadly",
 "version": "0.14.1",
 "license": "GPLv2",
 "url": "https://github.com/ndeadly/MissionControl/releases",
 "category": "tool",
 "details": "Use controllers from other consoles natively on your Nintendo Switch via Bluetooth. No dongles or other external hardware neccessary.\\n\\nNotice: After installing this package, reboot your console to activate the module!\\n\\nFeatures\\n\\nSupport the dev on Ko-fi: https://ko-fi.com/J3J01BZZ6\\nDiscord server: https://discord.gg/gegfNZ5Ucz\\n\\nSupports all Switch firmware versions.\\nConnect up to 8 non-switch Bluetooth controllers simultaneously without any additional hardware.\\nMake use of native HOS menus for controller pairing, button remapping (firmware 10.0.0+) etc.\\nSupport for rumble and motion controls (compatible controllers only)\\nLow input lag.\\nFile-based virtual controller memory allowing for data such as analog stick calibration to be stored and retrieved.\\nUnlocks such as button remapping and stick calibration for third-party Licensed Pro Controllers.\\nEnables use of JoyConDroid without root access.\\nSpoofing of host Bluetooth adapter name and address.\\nmc.mitm module adds extension IPC commands that can be used to interact with the bluetooth process without interfering with the state of the system.\\nSupported Controllers\\n\\nCurrently, the following controllers are supported. If you have a third-party variant of one of the below, or a Bluetooth controller that isn't listed, consider submitting a controller request issue.\\n\\nNintendo Wii Remote + extensions (Nunchuck, Classic Controller, Classic Controller Pro, SNES Mini, TaTaCon (Taiko drum), MotionPlus)\\nNintendo Wii Balance Board (experimental)\\nNintendo WiiU Pro Controller\\nSony Dualshock3 (Playstation 3) Controller\\nSony DualShock4 (Playstation 4) Controller\\nSony Dualsense (Playstation 5) Controller\\nSony Dualsense Edge Controller\\nMicrosoft Xbox One S/X Controller (not to be confused with Series S/X controllers - these use Bluetooth LE, which isn't currently supported)*\\nMicrosoft Xbox Elite Wireless Controller Series 2\\nNVidia Shield Controller (2017 Model)\\nOuya Controller\\nGamestick Controller\\nGembox Controller\\niCade Controller\\nIpega Controllers (7197, 9017s, 9023, 9055, 9062S, 9076, 9078, 9087, 9096 confirmed working. Others may also work)\\ng910 Wireless Bluetooth Controller\\nXiaomi Mi Controller\\nSteelseries Free\\nSteelseries Nimbus\\nSteelseries Stratus Duo\\nSteelseries Stratus XL\\nGameSir G3s\\nGameSir G4s\\nGameSir T1s\\nGameSir T2a\\nHori Onyx\\n8BitDo SN30 Pro Xbox Cloud Gaming Edition\\n8BitDo Ultimate 2.4G Wireless Controller\\n8BitDo ZERO (Most other 8BitDo controllers have a Switch mode available. May require firmware update)\\nPowerA Moga Hero\\nPowerA Moga Pro\\nPowerA Moga Pro 2\\nMad-Catz C.T.R.L.R\\nMad-Catz L.Y.N.X 3\\nRazer Raiju Tournament\\nRazer Raiju Ultimate\\nRazer Serval\\nMocute 050\\nMocute 053\\nGen Game S3\\nAtGames Legends Pinball Controller + Arcade Control Panel\\nHyperkin Scout\\nBetop 2585N2\\nAtari Wireless Modern Controller\\nSCUF Vantage 2\\n*Not all Xbox One wireless controllers support Bluetooth. Older variants use a proprietary 2.4Ghz protocol and cannot be used with the Switch. See here for information on identifying the Bluetooth variant.\\n\\nRequirements\\n\\nHackable Nintendo Switch running an up-to-date version of Atmosph\u00e8re custom firmware. Other custom firmwares are not supported.\\nCompatible Bluetooth controller",
 "changelog": "v0.14.1\\nThis release adds support for firmware 21.1.0, and fixes a minor button mapping bug from the previous release. See below for the full changelog.\\n\\nNew users landing on this release page should first check out the readme on the main project page: https://github.com/ndeadly/MissionControlreadme for the official project documentation. There you can find installation and usage instructions along with an FAQ section that will answer most of your questions.\\n\\n Changelog\\n- Added support for firmware 21.1.0\\n- Fixed swapped L/R triggers for Amazon Fire TV Game Controller\\n\\nv0.14.0\\nThis release adds support for firmware 21.0.0, some new controllers, and a bugfix. See below for the full changelog.\\n\\nNew users landing on this release page should first check out the readme on the main project page: https://github.com/ndeadly/MissionControlreadme for the official project documentation. There you can find installation and usage instructions along with an FAQ section that will answer most of your questions.\\n\\n Changelog\\n- Added full support for firmware 21.0.0\\n- Added support for Amazon Fire TV Game Controller\\n- Added support for GameSir G7 Pro Controller\\n- Fixed an issue where Joycon clones without the (L) or (R) designator in the name string would be detected incorrectly\\n\\nNew users landing on this release page should first check out the readme on the main project page: https://github.com/ndeadly/MissionControlreadme for the official project documentation. There you can find installation and usage instructions along with an FAQ section that will answer most of your questions.\\n\\nv0.13.6\\n\\nThis release adds support for firmware 20.5.0.\\n\\nNew users landing on this release page should first check out the readme on the main project page: https://github.com/ndeadly/MissionControlreadme for the official project documentation. There you can find installation and usage instructions along with an FAQ section that will answer most of your questions.\\n\\n Changelog\\n- Recompiled with latest Atmosphere-libs commit for 20.5.0 support\\n\\nv0.13.5\\nThis release adds support for firmware 20.4.0, and a new configuration option for disabling support for pairing Dualshock 3 controllers via USB.\\n\\nThe new configuration option dualshock3_enable_usb_pairing allows for disabling USB pairing of Dualshock 3 controllers for compatibility with sys-con. When both sysmodules are running, Dualshock 3 controllers can't be used via USB due to conflicting interface filters for detecting the controller. Disabling this option allows sys-con to detect the controller, at the expense of being able to pair them for wireless use.\\n\\n_Note: Dualshock 3 controllers can still be used wirelessly with this option disabled, they just must be paired prior to disabling it_\\n\\nNew users landing on this release page should first check out the readme on the main project page: https://github.com/ndeadly/MissionControlreadme for the official project documentation. There you can find installation and usage instructions along with an FAQ section that will answer most of your questions.\\n\\n Changelog\\n- Added support for firmware 20.4.0\\n- Added option to config .ini for disabling dualshock 3 usb pairing\\n\\nv0.13.4\\n- Added support for firmware 20.3.0"
}